{
  "rules": [
    { "pathname": "/robots.txt", "dest": "robots.alpha.chat.grindery.io" },
    { "pathname": "/api", "dest": "api.alpha.chat.grindery.io" },
    { "pathname": "/api/**", "dest": "api.alpha.chat.grindery.io" },
    { "pathname": "/auth", "dest": "api.alpha.chat.grindery.io" },
    { "pathname": "/auth/**", "dest": "api.alpha.chat.grindery.io" },
    { "pathname": "/websocket", "dest": "api.alpha.chat.grindery.io" },
    { "pathname": "/websocket/**", "dest": "api.alpha.chat.grindery.io" },
    { "dest": "hyperion.alpha.chat.grindery.io" }
  ]
}
